pytest_docker/__init__.py
pytest_docker_butla-0.7.0.dist-info/DESCRIPTION.rst
pytest_docker_butla-0.7.0.dist-info/METADATA
pytest_docker_butla-0.7.0.dist-info/RECORD
pytest_docker_butla-0.7.0.dist-info/WHEEL
pytest_docker_butla-0.7.0.dist-info/entry_points.txt
pytest_docker_butla-0.7.0.dist-info/metadata.json
pytest_docker_butla-0.7.0.dist-info/top_level.txt
