Metadata-Version: 2.0
Name: pytest-docker-butla
Version: 0.7.0
Summary: UNKNOWN
Home-page: https://github.com/AndreLouisCaron/pytest-docker
Author: Andre Caron
Author-email: andre.l.caron@gmail.com
License: MIT
Keywords: docker,docker-compose,pytest
Platform: UNKNOWN
Classifier: Framework :: Pytest
Classifier: Development Status :: 3 - Alpha
Classifier: License :: OSI Approved :: MIT License
Classifier: Programming Language :: Python
Classifier: Programming Language :: Python :: 2.7
Classifier: Programming Language :: Python :: 3.5
Classifier: Topic :: Utilities
Classifier: Intended Audience :: Developers
Classifier: Operating System :: Unix
Classifier: Operating System :: POSIX
Classifier: Operating System :: Microsoft :: Windows
Requires-Dist: attrs (>=16)
